<annotation>
	<folder></folder>
	<filename>GOPR0138_MP4-94_jpg.rf.1018a063932251d075e40c17979f5307.jpg</filename>
	<path>GOPR0138_MP4-94_jpg.rf.1018a063932251d075e40c17979f5307.jpg</path>
	<source>
		<database>roboflow.com</database>
	</source>
	<size>
		<width>416</width>
		<height>416</height>
		<depth>3</depth>
	</size>
	<segmented>0</segmented>
	<object>
		<name>Persona</name>
		<pose>Unspecified</pose>
		<truncated>0</truncated>
		<difficult>0</difficult>
		<occluded>0</occluded>
		<bndbox>
			<xmin>81</xmin>
			<xmax>88</xmax>
			<ymin>261</ymin>
			<ymax>281</ymax>
		</bndbox>
	</object>
	<object>
		<name>Persona</name>
		<pose>Unspecified</pose>
		<truncated>0</truncated>
		<difficult>0</difficult>
		<occluded>0</occluded>
		<bndbox>
			<xmin>84</xmin>
			<xmax>90</xmax>
			<ymin>257</ymin>
			<ymax>277</ymax>
		</bndbox>
	</object>
	<object>
		<name>Persona</name>
		<pose>Unspecified</pose>
		<truncated>0</truncated>
		<difficult>0</difficult>
		<occluded>0</occluded>
		<bndbox>
			<xmin>225</xmin>
			<xmax>231</xmax>
			<ymin>276</ymin>
			<ymax>300</ymax>
		</bndbox>
	</object>
	<object>
		<name>Persona</name>
		<pose>Unspecified</pose>
		<truncated>0</truncated>
		<difficult>0</difficult>
		<occluded>0</occluded>
		<bndbox>
			<xmin>196</xmin>
			<xmax>200</xmax>
			<ymin>200</ymin>
			<ymax>213</ymax>
		</bndbox>
	</object>
	<object>
		<name>Persona</name>
		<pose>Unspecified</pose>
		<truncated>0</truncated>
		<difficult>0</difficult>
		<occluded>0</occluded>
		<bndbox>
			<xmin>201</xmin>
			<xmax>205</xmax>
			<ymin>201</ymin>
			<ymax>213</ymax>
		</bndbox>
	</object>
</annotation>
